MANIFEST.in
requirements.txt
setup.py
cocaine/__init__.py
cocaine/cli/__init__.py
cocaine/cli/cli.py
cocaine/cli/client.1.py
cocaine/cli/client.py
cocaine/cli/config_reader.py
cocaine/cli/resource.py
cocaine/cli/resources.py
cocaine/cli/util.py
cocaine/cli/webcli.py
cocaine/cli/webcli2.py
cocaine/cli/webcli3.py
cocaine/cli/webcli4.py
cocaine_cli.egg-info/PKG-INFO
cocaine_cli.egg-info/SOURCES.txt
cocaine_cli.egg-info/dependency_links.txt
cocaine_cli.egg-info/entry_points.txt
cocaine_cli.egg-info/namespace_packages.txt
cocaine_cli.egg-info/not-zip-safe
cocaine_cli.egg-info/requires.txt
cocaine_cli.egg-info/top_level.txt
tests/requirements.txt