Metadata-Version: 1.1
Name: cocaine-cli
Version: 0.12.0-alpha15
Summary: Cocaine Cloud Management Tool.
Home-page: https://github.com/cocaine/cocaine-pipeline
Author: Dmitry Unkovsky
Author-email: oil.crayons@gmail.com
License: LGPLv3+
Platform: Linux
Platform: BSD
Platform: MacOS
Classifier: Programming Language :: Python
Classifier: Programming Language :: Python :: 2.7
Classifier: Programming Language :: Python :: Implementation :: CPython
Classifier: Development Status :: 2 - Pre-Alpha
